poetry_project_example_pypi/__init__.py
poetry_project_example_pypi/example.py
poetry_project_example_pypi-0.1.0.dist-info/WHEEL
poetry_project_example_pypi-0.1.0.dist-info/METADATA
poetry_project_example_pypi-0.1.0.dist-info/RECORD
