Metadata-Version: 2.1
Name: poetry-project-example-pypi
Version: 0.1.0
Summary: 
Author: mpakdel-chwy
Author-email: mpakdel@chewy.com
Requires-Python: >=3.9,<4.0
Classifier: Programming Language :: Python :: 3
Classifier: Programming Language :: Python :: 3.9
Classifier: Programming Language :: Python :: 3.10
Classifier: Programming Language :: Python :: 3.11
Requires-Dist: pandas (>=1.5.1,<2.0.0)
